fixcloudutils/__init__.py
fixcloudutils/py.typed
fixcloudutils/service.py
fixcloudutils/types.py
fixcloudutils/util.py
fixcloudutils/arangodb/__init__.py
fixcloudutils/arangodb/arangodb_extensions.py
fixcloudutils/arangodb/async_arangodb.py
fixcloudutils/arangodb/entitydb.py
fixcloudutils/asyncio/__init__.py
fixcloudutils/asyncio/async_extensions.py
fixcloudutils/asyncio/periodic.py
fixcloudutils/asyncio/process_pool.py
fixcloudutils/asyncio/timed.py
fixcloudutils/logging/__init__.py
fixcloudutils/logging/json_logger.py
fixcloudutils/logging/prometheus_counter.py
fixcloudutils/redis/__init__.py
fixcloudutils/redis/cache.py
fixcloudutils/redis/event_stream.py
fixcloudutils/redis/lock.py
fixcloudutils/redis/pub_sub.py
fixcloudutils/redis/worker_queue.py
fixcloudutils-1.15.1.dist-info/LICENSE
fixcloudutils-1.15.1.dist-info/METADATA
fixcloudutils-1.15.1.dist-info/WHEEL
fixcloudutils-1.15.1.dist-info/top_level.txt
fixcloudutils-1.15.1.dist-info/RECORD
