Metadata-Version: 2.1
Name: fixcloudutils
Version: 1.15.1
Summary: Utilities for fixcloud.
Author: Some Engineering Inc.
License: GNU AFFERO GENERAL PUBLIC LICENSE
Project-URL: Homepage, https://fix.tt
Classifier: Programming Language :: Python :: 3
Requires-Python: >=3.9
License-File: LICENSE
Requires-Dist: attrs
Requires-Dist: cattrs
Provides-Extra: arango
Requires-Dist: python-arango; extra == "arango"
Provides-Extra: prometheus
Requires-Dist: prometheus-client; extra == "prometheus"
Provides-Extra: redis
Requires-Dist: redis; extra == "redis"
Requires-Dist: arq; extra == "redis"
Provides-Extra: test
Requires-Dist: black; extra == "test"
Requires-Dist: coverage; extra == "test"
Requires-Dist: flake8; extra == "test"
Requires-Dist: hypothesis; extra == "test"
Requires-Dist: mypy; extra == "test"
Requires-Dist: pep8-naming; extra == "test"
Requires-Dist: pip-tools; extra == "test"
Requires-Dist: pylint; extra == "test"
Requires-Dist: pytest; extra == "test"
Requires-Dist: pytest-asyncio; extra == "test"
Requires-Dist: pytest-cov; extra == "test"
Requires-Dist: tox; extra == "test"
